rusta_spider/.gitignore
rusta_spider/__init__.py
rusta_spider/items.py
rusta_spider/middlewares.py
rusta_spider/pipelines.py
rusta_spider/requirements.txt
rusta_spider/scrapy.cfg
rusta_spider/settings.py
rusta_spider/files/constants.py
rusta_spider/spiders/__init__.py
rusta_spider/spiders/rusta_spider.py
rusta_spider/sql/all_active_articles_de.sql
rusta_spider/sql/all_active_articles_fi.sql
rusta_spider/sql/all_active_articles_no.sql
rusta_spider/sql/all_active_articles_se.sql
rusta_spider/sql/campaign_of_the_week.sql
rusta_spider/sql/package_price.sql
rusta_spider/sql/rolling_campaigns.sql
rusta_spider/tools/__init__.py
rusta_spider/tools/logger.py
rusta_spider-0.0.3.dist-info/METADATA
rusta_spider-0.0.3.dist-info/WHEEL
rusta_spider-0.0.3.dist-info/licenses/LICENSE
rusta_spider-0.0.3.dist-info/RECORD
